check_bitdefender-1.0.5.dist-info/METADATA
check_bitdefender-1.0.5.dist-info/WHEEL
check_bitdefender-1.0.5.dist-info/entry_points.txt
check_bitdefender-1.0.5.dist-info/licenses/LICENSE
check_bitdefender/__init__.py
check_bitdefender/__main__.py
check_bitdefender/check_bitdefender.py
check_bitdefender/cli/__init__.py
check_bitdefender/cli/__main__.py
check_bitdefender/cli/commands/__init__.py
check_bitdefender/cli/commands/detail.py
check_bitdefender/cli/commands/endpoints.py
check_bitdefender/cli/commands/lastscan.py
check_bitdefender/cli/commands/lastseen.py
check_bitdefender/cli/commands/onboarding.py
check_bitdefender/cli/decorators.py
check_bitdefender/cli/handlers.py
check_bitdefender/core/__init__.py
check_bitdefender/core/auth.py
check_bitdefender/core/config.py
check_bitdefender/core/defender.py
check_bitdefender/core/exceptions.py
check_bitdefender/core/logging_config.py
check_bitdefender/core/nagios.py
check_bitdefender/services/__init__.py
check_bitdefender/services/detail_service.py
check_bitdefender/services/endpoint_service.py
check_bitdefender/services/lastscan_service.py
check_bitdefender/services/lastseen_service.py
check_bitdefender/services/models.py
check_bitdefender/services/onboarding_service.py
check_bitdefender-1.0.5.dist-info/RECORD
