Metadata-Version: 2.1
Name: check-bitdefender
Version: 1.0.5
Summary: A Nagios plugin for monitoring BitDefender GravityZone API endpoints
Keywords: nagios,monitoring,bitdefender,gravityzone,api,endpoint-security
Author-Email: ldvchosal <ldvchosal@github.com>
License: MIT
Classifier: Development Status :: 5 - Production/Stable
Classifier: Intended Audience :: System Administrators
Classifier: License :: OSI Approved :: MIT License
Classifier: Operating System :: OS Independent
Classifier: Programming Language :: Python :: 3
Classifier: Programming Language :: Python :: 3.9
Classifier: Programming Language :: Python :: 3.10
Classifier: Programming Language :: Python :: 3.11
Classifier: Topic :: System :: Monitoring
Classifier: Topic :: System :: Systems Administration
Project-URL: Homepage, https://github.com/lduchosal/check_bitdefender
Project-URL: Bug Reports, https://github.com/lduchosal/check_bitdefender/issues
Project-URL: Source, https://github.com/lduchosal/check_bitdefender
Project-URL: Documentation, https://github.com/lduchosal/check_bitdefender/blob/main/README.md
Requires-Python: >=3.9
Requires-Dist: nagiosplugin>=1.4.0
Requires-Dist: click<9.0,>=8.0
Requires-Dist: requests>=2.32.5
